casting/cast/sync/__init__.py
casting/cast/sync/cbsync.py
casting/cast/sync/conflict.py
casting/cast/sync/hsync.py
casting/cast/sync/index.py
casting/cast/sync/rename_cascade.py
cast_sync-0.1.6.dist-info/WHEEL
cast_sync-0.1.6.dist-info/METADATA
cast_sync-0.1.6.dist-info/RECORD
