Metadata-Version: 2.3
Name: cast-sync
Version: 0.1.6
Summary: Sync engine for Cast - 3-way sync and conflict handling
Requires-Dist: cast-core
Requires-Dist: rich>=13.0.0
Requires-Dist: ruamel-yaml>=0.18.0
Requires-Dist: pytest>=8.3.0 ; extra == 'dev'
Requires-Python: >=3.13
Provides-Extra: dev
